{"id": 347685, "slug": "tournament/kombat-cup-road-to-combo-breaker/event/kombat-cup", "name": "Kombat Cup", "startAt": 1556474400, "sets": {"pageInfo": {"total": 758}, "nodes": [{"id": 20104125, "games": [{"id": 1826101, "setId": 20104125, "winnerId": 2998028, "selections": [{"id": "2374513", "selectionType": "CHARACTER", "selectionValue": 1456, "entrantId": 3017224}, {"id": "2374514", "selectionType": "CHARACTER", "selectionValue": 1475, "entrantId": 2998028}]}, {"id": 1826104, "setId": 20104125, "winnerId": 3017224, "selections": [{"id": "2374519", "selectionType": "CHARACTER", "selectionValue": 1475, "entrantId": 2998028}, {"id": "2374520", "selectionType": "CHARACTER", "selectionValue": 1456, "entrantId": 3017224}]}, {"id": 1826157, "setId": 20104125, "winnerId": 2998028, "selections": [{"id": "2374601", "selectionType": "CHARACTER", "selectionValue": 1456, "entrantId": 3017224}, {"id": "2374602", "selectionType": "CHARACTER", "selectionValue": 1475, "entrantId": 2998028}]}], "slots": [{"standing": {"entrant": {"id": 3017224, "name": "Yungmonster12"}, "placement": 2, "stats": {"score": {"label": "Score", "value": 1, "displayValue": "1"}}}}, {"standing": {"entrant": {"id": 2998028, "name": "LeMarrine"}, "placement": 1, "stats": {"score": {"label": "Score", "value": 2, "displayValue": "2"}}}}]}, {"id": 20104504, "games": null, "slots": [{"standing": {"entrant": {"id": 3002913, "name": "RagingRicans"}, "placement": 2, "stats": {"score": {"label": "Score", "value": -1, "displayValue": "-1"}}}}, {"standing": {"entrant": {"id": 3001692, "name": "Tactaziumv"}, "placement": 1, "stats": {"score": {"label": "Score", "value": 0, "displayValue": "0"}}}}]}, {"id": 20103358, "games": [{"id": 1826211, "setId": 20103358, "winnerId": 3007349, "selections": [{"id": "2374693", "selectionType": "CHARACTER", "selectionValue": 1469, "entrantId": 3007349}, {"id": "2374694", "selectionType": "CHARACTER", "selectionValue": 1460, "entrantId": 3020080}]}, {"id": 1826213, "setId": 20103358, "winnerId": 3020080, "selections": [{"id": "2374697", "selectionType": "CHARACTER", "selectionValue": 1469, "entrantId": 3007349}, {"id": "2374698", "selectionType": "CHARACTER", "selectionValue": 1460, "entrantId": 3020080}]}, {"id": 1826224, "setId": 20103358, "winnerId": 3007349, "selections": [{"id": "2374719", "selectionType": "CHARACTER", "selectionValue": 1460, "entrantId": 3020080}, {"id": "2374720", "selectionType": "CHARACTER", "selectionValue": 1469, "entrantId": 3007349}]}], "slots": [{"standing": {"entrant": {"id": 3020080, "name": "ANBU_JPatlan"}, "placement": 2, "stats": {"score": {"label": "Score", "value": 1, "displayValue": "1"}}}}, {"standing": {"entrant": {"id": 3007349, "name": "SiK | Cam is black"}, "placement": 1, "stats": {"score": {"label": "Score", "value": 2, "displayValue": "2"}}}}]}, {"id": 20103550, "games": [{"id": 1826528, "setId": 20103550, "winnerId": 3015946, "selections": [{"id": "2375196", "selectionType": "CHARACTER", "selectionValue": 1479, "entrantId": 3001886}, {"id": "2375197", "selectionType": "CHARACTER", "selectionValue": 1470, "entrantId": 3015946}]}, {"id": 1826532, "setId": 20103550, "winnerId": 3015946, "selections": [{"id": "2375204", "selectionType": "CHARACTER", "selectionValue": 1470, "entrantId": 3015946}, {"id": "2375205", "selectionType": "CHARACTER", "selectionValue": 1479, "entrantId": 3001886}]}], "slots": [{"standing": {"entrant": {"id": 3015946, "name": "Crescent | DevilTrigger"}, "placement": 1, "stats": {"score": {"label": "Score", "value": 2, "displayValue": "2"}}}}, {"standing": {"entrant": {"id": 3001886, "name": "CrazyFingers"}, "placement": 2, "stats": {"score": {"label": "Score", "value": 0, "displayValue": "0"}}}}]}, {"id": 20103740, "games": [{"id": 1826170, "setId": 20103740, "winnerId": 2998966, "selections": [{"id": "2374621", "selectionType": "CHARACTER", "selectionValue": 1478, "entrantId": 2998966}, {"id": "2374622", "selectionType": "CHARACTER", "selectionValue": 1458, "entrantId": 3018166}]}, {"id": 1826239, "setId": 20103740, "winnerId": 2998966, "selections": [{"id": "2374749", "selectionType": "CHARACTER", "selectionValue": 1478, "entrantId": 2998966}, {"id": "2374750", "selectionType": "CHARACTER", "selectionValue": 1458, "entrantId": 3018166}]}], "slots": [{"standing": {"entrant": {"id": 2998966, "name": "Verlara"}, "placement": 1, "stats": {"score": {"label": "Score", "value": 2, "displayValue": "2"}}}}, {"standing": {"entrant": {"id": 3018166, "name": "NY | Sarunai-"}, "placement": 2, "stats": {"score": {"label": "Score", "value": 0, "displayValue": "0"}}}}]}, {"id": 20103933, "games": [{"id": 1826734, "setId": 20103933, "winnerId": 3019594, "selections": [{"id": "2375489", "selectionType": "CHARACTER", "selectionValue": 1456, "entrantId": 3019594}, {"id": "2375490", "selectionType": "CHARACTER", "selectionValue": 1462, "entrantId": 3018839}]}, {"id": 1826735, "setId": 20103933, "winnerId": 3019594, "selections": [{"id": "2375491", "selectionType": "CHARACTER", "selectionValue": 1456, "entrantId": 3019594}, {"id": "2375492", "selectionType": "CHARACTER", "selectionValue": 1462, "entrantId": 3018839}]}], "slots": [{"standing": {"entrant": {"id": 3019594, "name": "Bdon"}, "placement": 1, "stats": {"score": {"label": "Score", "value": 2, "displayValue": "2"}}}}, {"standing": {"entrant": {"id": 3018839, "name": "BoiledWalnut"}, "placement": 2, "stats": {"score": {"label": "Score", "value": 0, "displayValue": "0"}}}}]}, {"id": 20103167, "games": null, "slots": [{"standing": {"entrant": {"id": 2998104, "name": "KillaCam_FGC"}, "placement": 2, "stats": {"score": {"label": "Score", "value": 0, "displayValue": "0"}}}}, {"standing": {"entrant": {"id": 3005785, "name": "Kickbykick"}, "placement": 1, "stats": {"score": {"label": "Score", "value": 2, "displayValue": "2"}}}}]}, {"id": 20104122, "games": [{"id": 1826321, "setId": 20104122, "winnerId": 2998437, "selections": [{"id": "2374895", "selectionType": "CHARACTER", "selectionValue": 1480, "entrantId": 2998437}, {"id": "2374896", "selectionType": "CHARACTER", "selectionValue": 1475, "entrantId": 2999945}]}, {"id": 1826325, "setId": 20104122, "winnerId": 2999945, "selections": [{"id": "2374903", "selectionType": "CHARACTER", "selectionValue": 1480, "entrantId": 2998437}, {"id": "2374904", "selectionType": "CHARACTER", "selectionValue": 1475, "entrantId": 2999945}]}, {"id": 1826330, "setId": 20104122, "winnerId": 2999945, "selections": [{"id": "2374911", "selectionType": "CHARACTER", "selectionValue": 1475, "entrantId": 2999945}, {"id": "2374912", "selectionType": "CHARACTER", "selectionValue": 1480, "entrantId": 2998437}]}], "slots": [{"standing": {"entrant": {"id": 2999945, "name": "Fatal"}, "placement": 1, "stats": {"score": {"label": "Score", "value": 2, "displayValue": "2"}}}}, {"standing": {"entrant": {"id": 2998437, "name": "sooneo"}, "placement": 2, "stats": {"score": {"label": "Score", "value": 1, "displayValue": "1"}}}}]}, {"id": 20104124, "games": [{"id": 1826299, "setId": 20104124, "winnerId": 3014320, "selections": [{"id": "2374865", "selectionType": "CHARACTER", "selectionValue": 1461, "entrantId": 3014320}, {"id": "2374866", "selectionType": "CHARACTER", "selectionValue": 1469, "entrantId": 3000229}]}, {"id": 1826304, "setId": 20104124, "winnerId": 3014320, "selections": [{"id": "2374873", "selectionType": "CHARACTER", "selectionValue": 1461, "entrantId": 3014320}, {"id": "2374874", "selectionType": "CHARACTER", "selectionValue": 1469, "entrantId": 3000229}]}], "slots": [{"standing": {"entrant": {"id": 3014320, "name": "DF | Grr"}, "placement": 1, "stats": {"score": {"label": "Score", "value": 2, "displayValue": "2"}}}}, {"standing": {"entrant": {"id": 3000229, "name": "Zayah"}, "placement": 2, "stats": {"score": {"label": "Score", "value": 0, "displayValue": "0"}}}}]}, {"id": 20104313, "games": [{"id": 1826278, "setId": 20104313, "winnerId": 3016536, "selections": [{"id": "2374825", "selectionType": "CHARACTER", "selectionValue": 1479, "entrantId": 3016536}, {"id": "2374826", "selectionType": "CHARACTER", "selectionValue": 1469, "entrantId": 2997996}]}, {"id": 1826280, "setId": 20104313, "winnerId": 2997996, "selections": [{"id": "2374829", "selectionType": "CHARACTER", "selectionValue": 1479, "entrantId": 3016536}, {"id": "2374830", "selectionType": "CHARACTER", "selectionValue": 1469, "entrantId": 2997996}]}, {"id": 1826284, "setId": 20104313, "winnerId": 2997996, "selections": [{"id": "2374837", "selectionType": "CHARACTER", "selectionValue": 1469, "entrantId": 2997996}, {"id": "2374838", "selectionType": "CHARACTER", "selectionValue": 1479, "entrantId": 3016536}]}], "slots": [{"standing": {"entrant": {"id": 2997996, "name": "Gambit"}, "placement": 1, "stats": {"score": {"label": "Score", "value": 2, "displayValue": "2"}}}}, {"standing": {"entrant": {"id": 3016536, "name": "King_CoRzz"}, "placement": 2, "stats": {"score": {"label": "Score", "value": 1, "displayValue": "1"}}}}]}, {"id": 20104506, "games": [{"id": 1825997, "setId": 20104506, "winnerId": 3018740, "selections": [{"id": "2374353", "selectionType": "CHARACTER", "selectionValue": 1477, "entrantId": 3018740}, {"id": "2374354", "selectionType": "CHARACTER", "selectionValue": 1462, "entrantId": 3020286}]}, {"id": 1826036, "setId": 20104506, "winnerId": 3018740, "selections": [{"id": "2374417", "selectionType": "CHARACTER", "selectionValue": 1477, "entrantId": 3018740}, {"id": "2374418", "selectionType": "CHARACTER", "selectionValue": 1462, "entrantId": 3020286}]}], "slots": [{"standing": {"entrant": {"id": 3020286, "name": "NewJetRadio"}, "placement": 2, "stats": {"score": {"label": "Score", "value": 0, "displayValue": "0"}}}}, {"standing": {"entrant": {"id": 3018740, "name": "Stabs"}, "placement": 1, "stats": {"score": {"label": "Score", "value": 2, "displayValue": "2"}}}}]}, {"id": 20103551, "games": [{"id": 1826013, "setId": 20103551, "winnerId": 3012593, "selections": [{"id": "2374381", "selectionType": "CHARACTER", "selectionValue": 1468, "entrantId": 3012593}, {"id": "2374382", "selectionType": "CHARACTER", "selectionValue": 1473, "entrantId": 3012266}]}, {"id": 1826015, "setId": 20103551, "winnerId": 3012593, "selections": [{"id": "2374385", "selectionType": "CHARACTER", "selectionValue": 1468, "entrantId": 3012593}, {"id": "2374386", "selectionType": "CHARACTER", "selectionValue": 1473, "entrantId": 3012266}]}], "slots": [{"standing": {"entrant": {"id": 3012266, "name": "akawebbs"}, "placement": 2, "stats": {"score": {"label": "Score", "value": 0, "displayValue": "0"}}}}, {"standing": {"entrant": {"id": 3012593, "name": "UnbearableSkill"}, "placement": 1, "stats": {"score": {"label": "Score", "value": 2, "displayValue": "2"}}}}]}, {"id": 20103552, "games": [{"id": 1826303, "setId": 20103552, "winnerId": 3015331, "selections": [{"id": "2374871", "selectionType": "CHARACTER", "selectionValue": 1462, "entrantId": 3015331}, {"id": "2374872", "selectionType": "CHARACTER", "selectionValue": 1468, "entrantId": 2997835}]}, {"id": 1826323, "setId": 20103552, "winnerId": 3015331, "selections": [{"id": "2374899", "selectionType": "CHARACTER", "selectionValue": 1462, "entrantId": 3015331}, {"id": "2374900", "selectionType": "CHARACTER", "selectionValue": 1468, "entrantId": 2997835}]}], "slots": [{"standing": {"entrant": {"id": 3015331, "name": "FinalAbe"}, "placement": 1, "stats": {"score": {"label": "Score", "value": 2, "displayValue": "2"}}}}, {"standing": {"entrant": {"id": 2997835, "name": "SlayJay"}, "placement": 2, "stats": {"score": {"label": "Score", "value": 0, "displayValue": "0"}}}}]}, {"id": 20103742, "games": [{"id": 1826238, "setId": 20103742, "winnerId": 2997941, "selections": [{"id": "2374747", "selectionType": "CHARACTER", "selectionValue": 1475, "entrantId": 3007865}, {"id": "2374748", "selectionType": "CHARACTER", "selectionValue": 1463, "entrantId": 2997941}]}, {"id": 1826277, "setId": 20103742, "winnerId": 2997941, "selections": [{"id": "2374823", "selectionType": "CHARACTER", "selectionValue": 1463, "entrantId": 2997941}, {"id": "2374824", "selectionType": "CHARACTER", "selectionValue": 1475, "entrantId": 3007865}]}], "slots": [{"standing": {"entrant": {"id": 2997941, "name": "moulu"}, "placement": 1, "stats": {"score": {"label": "Score", "value": 2, "displayValue": "2"}}}}, {"standing": {"entrant": {"id": 3007865, "name": "Smack"}, "placement": 2, "stats": {"score": {"label": "Score", "value": 0, "displayValue": "0"}}}}]}, {"id": 20103931, "games": [{"id": 1826266, "setId": 20103931, "winnerId": 3014554, "selections": [{"id": "2374801", "selectionType": "CHARACTER", "selectionValue": 1461, "entrantId": 3014554}, {"id": "2374802", "selectionType": "CHARACTER", "selectionValue": 1472, "entrantId": 2999238}]}, {"id": 1826276, "setId": 20103931, "winnerId": 3014554, "selections": [{"id": "2374821", "selectionType": "CHARACTER", "selectionValue": 1461, "entrantId": 3014554}, {"id": "2374822", "selectionType": "CHARACTER", "selectionValue": 1472, "entrantId": 2999238}]}], "slots": [{"standing": {"entrant": {"id": 3014554, "name": "Kevoxreborn"}, "placement": 1, "stats": {"score": {"label": "Score", "value": 2, "displayValue": "2"}}}}, {"standing": {"entrant": {"id": 2999238, "name": "ANBU_Getreked"}, "placement": 2, "stats": {"score": {"label": "Score", "value": 0, "displayValue": "0"}}}}]}, {"id": 20103166, "games": [{"id": 1826205, "setId": 20103166, "winnerId": 3019252, "selections": [{"id": "2374681", "selectionType": "CHARACTER", "selectionValue": 1462, "entrantId": 3007771}, {"id": "2374682", "selectionType": "CHARACTER", "selectionValue": 1464, "entrantId": 3019252}]}, {"id": 1826209, "setId": 20103166, "winnerId": 3019252, "selections": [{"id": "2374689", "selectionType": "CHARACTER", "selectionValue": 1464, "entrantId": 3019252}, {"id": "2374690", "selectionType": "CHARACTER", "selectionValue": 1462, "entrantId": 3007771}]}], "slots": [{"standing": {"entrant": {"id": 3019252, "name": "SiK__Killadilla"}, "placement": 1, "stats": {"score": {"label": "Score", "value": 2, "displayValue": "2"}}}}, {"standing": {"entrant": {"id": 3007771, "name": "DramanK"}, "placement": 2, "stats": {"score": {"label": "Score", "value": 0, "displayValue": "0"}}}}]}, {"id": 20104314, "games": [{"id": 1826313, "setId": 20104314, "winnerId": 3009094, "selections": [{"id": "2374883", "selectionType": "CHARACTER", "selectionValue": 1475, "entrantId": 3009094}, {"id": "2374884", "selectionType": "CHARACTER", "selectionValue": 1470, "entrantId": 3016807}]}, {"id": 1826345, "setId": 20104314, "winnerId": 3009094, "selections": [{"id": "2374931", "selectionType": "CHARACTER", "selectionValue": 1475, "entrantId": 3009094}, {"id": "2374932", "selectionType": "CHARACTER", "selectionValue": 1474, "entrantId": 3016807}]}], "slots": [{"standing": {"entrant": {"id": 3016807, "name": "ECG | night breed 9"}, "placement": 2, "stats": {"score": {"label": "Score", "value": 0, "displayValue": "0"}}}}, {"standing": {"entrant": {"id": 3009094, "name": "BSL | Four Loko"}, "placement": 1, "stats": {"score": {"label": "Score", "value": 2, "displayValue": "2"}}}}]}, {"id": 20104315, "games": [{"id": 1826065, "setId": 20104315, "winnerId": 3013947, "selections": [{"id": "2374465", "selectionType": "CHARACTER", "selectionValue": 1458, "entrantId": 3000167}, {"id": "2374466", "selectionType": "CHARACTER", "selectionValue": 1465, "entrantId": 3013947}]}, {"id": 1826155, "setId": 20104315, "winnerId": 3000167, "selections": [{"id": "2374597", "selectionType": "CHARACTER", "selectionValue": 1465, "entrantId": 3013947}, {"id": "2374598", "selectionType": "CHARACTER", "selectionValue": 1458, "entrantId": 3000167}]}, {"id": 1826162, "setId": 20104315, "winnerId": 3000167, "selections": [{"id": "2374609", "selectionType": "CHARACTER", "selectionValue": 1458, "entrantId": 3000167}, {"id": "2374610", "selectionType": "CHARACTER", "selectionValue": 1465, "entrantId": 3013947}]}], "slots": [{"standing": {"entrant": {"id": 3013947, "name": "ElitheCurry"}, "placement": 2, "stats": {"score": {"label": "Score", "value": 1, "displayValue": "1"}}}}, {"standing": {"entrant": {"id": 3000167, "name": "frankpriz"}, "placement": 1, "stats": {"score": {"label": "Score", "value": 2, "displayValue": "2"}}}}]}, {"id": 20104316, "games": [{"id": 1826087, "setId": 20104316, "winnerId": 3020629, "selections": [{"id": "2374491", "selectionType": "CHARACTER", "selectionValue": 1480, "entrantId": 3012245}, {"id": "2374492", "selectionType": "CHARACTER", "selectionValue": 1463, "entrantId": 3020629}]}, {"id": 1826090, "setId": 20104316, "winnerId": 3020629, "selections": [{"id": "2374497", "selectionType": "CHARACTER", "selectionValue": 1463, "entrantId": 3020629}, {"id": "2374498", "selectionType": "CHARACTER", "selectionValue": 1480, "entrantId": 3012245}]}], "slots": [{"standing": {"entrant": {"id": 3020629, "name": "Kinetic_Predator"}, "placement": 1, "stats": {"score": {"label": "Score", "value": 2, "displayValue": "2"}}}}, {"standing": {"entrant": {"id": 3012245, "name": "Rabbit"}, "placement": 2, "stats": {"score": {"label": "Score", "value": 0, "displayValue": "0"}}}}]}, {"id": 20104507, "games": [{"id": 1826024, "setId": 20104507, "winnerId": 3008066, "selections": [{"id": "2374399", "selectionType": "CHARACTER", "selectionValue": 1457, "entrantId": 3018804}, {"id": "2374400", "selectionType": "CHARACTER", "selectionValue": 1463, "entrantId": 3008066}]}, {"id": 1826027, "setId": 20104507, "winnerId": 3018804, "selections": [{"id": "2374405", "selectionType": "CHARACTER", "selectionValue": 1463, "entrantId": 3008066}, {"id": "2374406", "selectionType": "CHARACTER", "selectionValue": 1457, "entrantId": 3018804}]}, {"id": 1826032, "setId": 20104507, "winnerId": 3008066, "selections": [{"id": "2374411", "selectionType": "CHARACTER", "selectionValue": 1457, "entrantId": 3018804}, {"id": "2374412", "selectionType": "CHARACTER", "selectionValue": 1463, "entrantId": 3008066}]}], "slots": [{"standing": {"entrant": {"id": 3008066, "name": "Dark"}, "placement": 1, "stats": {"score": {"label": "Score", "value": 2, "displayValue": "2"}}}}, {"standing": {"entrant": {"id": 3018804, "name": "Mattix"}, "placement": 2, "stats": {"score": {"label": "Score", "value": 1, "displayValue": "1"}}}}]}, {"id": 20103357, "games": [{"id": 1826001, "setId": 20103357, "winnerId": 3006647, "selections": [{"id": "2374359", "selectionType": "CHARACTER", "selectionValue": 1462, "entrantId": 3006647}, {"id": "2374360", "selectionType": "CHARACTER", "selectionValue": 1475, "entrantId": 3001819}]}, {"id": 1826011, "setId": 20103357, "winnerId": 3006647, "selections": [{"id": "2374377", "selectionType": "CHARACTER", "selectionValue": 1462, "entrantId": 3006647}, {"id": "2374378", "selectionType": "CHARACTER", "selectionValue": 1475, "entrantId": 3001819}]}], "slots": [{"standing": {"entrant": {"id": 3006647, "name": "IKizzLE"}, "placement": 1, "stats": {"score": {"label": "Score", "value": 2, "displayValue": "2"}}}}, {"standing": {"entrant": {"id": 3001819, "name": "JIN863"}, "placement": 2, "stats": {"score": {"label": "Score", "value": 0, "displayValue": "0"}}}}]}, {"id": 20103359, "games": [{"id": 1826053, "setId": 20103359, "winnerId": 3018604, "selections": [{"id": "2374445", "selectionType": "CHARACTER", "selectionValue": 1457, "entrantId": 2998836}, {"id": "2374446", "selectionType": "CHARACTER", "selectionValue": 1469, "entrantId": 3018604}]}, {"id": 1826103, "setId": 20103359, "winnerId": 2998836, "selections": [{"id": "2374517", "selectionType": "CHARACTER", "selectionValue": 1469, "entrantId": 3018604}, {"id": "2374518", "selectionType": "CHARACTER", "selectionValue": 1457, "entrantId": 2998836}]}, {"id": 1826108, "setId": 20103359, "winnerId": 2998836, "selections": [{"id": "2374527", "selectionType": "CHARACTER", "selectionValue": 1457, "entrantId": 2998836}, {"id": "2374528", "selectionType": "CHARACTER", "selectionValue": 1469, "entrantId": 3018604}]}], "slots": [{"standing": {"entrant": {"id": 3018604, "name": "Slayeredhat"}, "placement": 2, "stats": {"score": {"label": "Score", "value": 1, "displayValue": "1"}}}}, {"standing": {"entrant": {"id": 2998836, "name": "DubTF86"}, "placement": 1, "stats": {"score": {"label": "Score", "value": 2, "displayValue": "2"}}}}]}, {"id": 20103360, "games": [{"id": 1826359, "setId": 20103360, "winnerId": 3013538, "selections": [{"id": "2374959", "selectionType": "CHARACTER", "selectionValue": 1478, "entrantId": 3013538}, {"id": "2374960", "selectionType": "CHARACTER", "selectionValue": 1475, "entrantId": 3003585}]}, {"id": 1826403, "setId": 20103360, "winnerId": 3013538, "selections": [{"id": "2375013", "selectionType": "CHARACTER", "selectionValue": 1478, "entrantId": 3013538}, {"id": "2375014", "selectionType": "CHARACTER", "selectionValue": 1475, "entrantId": 3003585}]}], "slots": [{"standing": {"entrant": {"id": 3013538, "name": "Station"}, "placement": 1, "stats": {"score": {"label": "Score", "value": 2, "displayValue": "2"}}}}, {"standing": {"entrant": {"id": 3003585, "name": "D-Que Beats"}, "placement": 2, "stats": {"score": {"label": "Score", "value": 0, "displayValue": "0"}}}}]}, {"id": 20103743, "games": [{"id": 1826329, "setId": 20103743, "winnerId": 3019879, "selections": [{"id": "2374909", "selectionType": "CHARACTER", "selectionValue": 1461, "entrantId": 3018953}, {"id": "2374910", "selectionType": "CHARACTER", "selectionValue": 1476, "entrantId": 3019879}]}, {"id": 1826404, "setId": 20103743, "winnerId": 3019879, "selections": [{"id": "2375015", "selectionType": "CHARACTER", "selectionValue": 1476, "entrantId": 3019879}, {"id": "2375016", "selectionType": "CHARACTER", "selectionValue": 1458, "entrantId": 3018953}]}], "slots": [{"standing": {"entrant": {"id": 3018953, "name": "Myztery_-BOT"}, "placement": 2, "stats": {"score": {"label": "Score", "value": 0, "displayValue": "0"}}}}, {"standing": {"entrant": {"id": 3019879, "name": "T7G | DjOn6"}, "placement": 1, "stats": {"score": {"label": "Score", "value": 2, "displayValue": "2"}}}}]}, {"id": 20103932, "games": [{"id": 1826333, "setId": 20103932, "winnerId": 3002420, "selections": [{"id": "2374917", "selectionType": "CHARACTER", "selectionValue": 1475, "entrantId": 3002420}, {"id": "2374918", "selectionType": "CHARACTER", "selectionValue": 1457, "entrantId": 3001831}]}, {"id": 1826340, "setId": 20103932, "winnerId": 3002420, "selections": [{"id": "2374925", "selectionType": "CHARACTER", "selectionValue": 1475, "entrantId": 3002420}, {"id": "2374926", "selectionType": "CHARACTER", "selectionValue": 1457, "entrantId": 3001831}]}], "slots": [{"standing": {"entrant": {"id": 3001831, "name": "Aarondamac"}, "placement": 2, "stats": {"score": {"label": "Score", "value": 0, "displayValue": "0"}}}}, {"standing": {"entrant": {"id": 3002420, "name": "Kuchikopi"}, "placement": 1, "stats": {"score": {"label": "Score", "value": 2, "displayValue": "2"}}}}]}]}}